anomaly_prediction/__init__.py
anomaly_prediction/datasets/__init__.py
anomaly_prediction/datasets/time_series_dataset.py
anomaly_prediction/experiments/__init__.py
anomaly_prediction/experiments/experiment_runner.py
anomaly_prediction/models/__init__.py
anomaly_prediction/models/simple_linear_model.py
anomaly_prediction/utils/__init__.py
anomaly_prediction/utils/cumulative_loss.py
anomaly_prediction/utils/plot_utils.py
anomaly_prediction-0.1.5.dist-info/METADATA
anomaly_prediction-0.1.5.dist-info/WHEEL
anomaly_prediction-0.1.5.dist-info/top_level.txt
anomaly_prediction-0.1.5.dist-info/RECORD
