Metadata-Version: 2.1
Name: anomaly-prediction
Version: 0.1.5
Summary: A library for anomaly prediction in time series data.
Home-page: https://github.com/JiangYou2025/AnomalyPrediction
Author: Jiang YOU
Author-email: jiang.you@esiee.fr
License: UNKNOWN
Platform: UNKNOWN
Classifier: Programming Language :: Python :: 3
Classifier: License :: OSI Approved :: MIT License
Classifier: Operating System :: OS Independent
Requires-Python: >=3.10
Requires-Dist: numpy
Requires-Dist: torch
Requires-Dist: matplotlib
Requires-Dist: scikit-learn
